text_to_sql_llm_py/__init__.py
text_to_sql_llm_py/text_to_sql.py
text_to_sql_llm_py-0.0.5.dist-info/METADATA
text_to_sql_llm_py-0.0.5.dist-info/WHEEL
text_to_sql_llm_py-0.0.5.dist-info/licenses/LICENSE
text_to_sql_llm_py-0.0.5.dist-info/RECORD
